kakuyomu/__init__.py
kakuyomu/settings.py
kakuyomu/types.py
kakuyomu/cli/__init__.py
kakuyomu/cli/main.py
kakuyomu/scrapers/__init__.py
kakuyomu/scrapers/scraping_my.py
kakuyomu/utils/__init__.py
kakuyomu/utils/web.py
kakuyomu-0.1.0.dist-info/METADATA
kakuyomu-0.1.0.dist-info/WHEEL
kakuyomu-0.1.0.dist-info/entry_points.txt
kakuyomu-0.1.0.dist-info/RECORD
