Metadata-Version: 2.1
Name: kakuyomu
Version: 0.1.0
Summary: Add your description here
Author-email: kokardy <mgc1028@gmail.com>
Requires-Python: >=3.12
Requires-Dist: beautifulsoup4>=4.12.2
Requires-Dist: pydantic>=2.5.3
Requires-Dist: requests>=2.31.0
